LICENSE
MANIFEST.in
README.rst
setup.py
ExEmGel.egg-info/PKG-INFO
ExEmGel.egg-info/SOURCES.txt
ExEmGel.egg-info/dependency_links.txt
ExEmGel.egg-info/top_level.txt
exemgel/__init__.py
exemgel/data_for_testing.py
exemgel/doc.py
exemgel/node.py
exemgel/read_config.py
exemgel/test_doc.py
exemgel/test_node.py
exemgel/test_read_config.py