Metadata-Version: 1.1
Name: ExEmGel
Version: 0.5
Summary: Simple xml reader
Home-page: https://github.com/thedavecollins/ExEmGel
Author: Dave Collins
Author-email: dave@hopest.net
License: MIT
Platform: UNKNOWN
Classifier: Intended Audience :: Developers
Classifier: Programming Language :: Python :: 2.7
Classifier: Programming Language :: Python :: 3.4
Classifier: License :: OSI Approved
Classifier: License :: OSI Approved :: MIT License
Classifier: Topic :: Text Processing
Classifier: Topic :: Text Processing :: Markup
Classifier: Topic :: Text Processing :: Markup :: XML
